MANIFEST.in
README.rst
setup.py
git_watcher.egg-info/PKG-INFO
git_watcher.egg-info/SOURCES.txt
git_watcher.egg-info/dependency_links.txt
git_watcher.egg-info/entry_points.txt
git_watcher.egg-info/pbr.json
git_watcher.egg-info/top_level.txt
watcher/__init__.py
watcher/main.py
watcher/watcher.py