Metadata-Version: 1.0
Name: git-watcher
Version: 0.7
Summary: git watcher will rebuild your repository when you push code to github.
Home-page: https://github.com/mymonkey110/git-watcher
Author: Michael Jiang
Author-email: mymonkey110@gmail.com
License: MIT License
Keywords: git,git-watcher,github,blog,hexo,baidu
Platform: UNKNOWN
Classifier: Development Status :: 4 - Beta
Classifier: Environment :: Console
Classifier: License :: OSI Approved :: MIT License
Classifier: Programming Language :: Python :: 2.7
Classifier: Topic :: Utilities
